odoo/addons/account_payment_term_partner_holiday/README.rst
odoo/addons/account_payment_term_partner_holiday/__init__.py
odoo/addons/account_payment_term_partner_holiday/__manifest__.py
odoo/addons/account_payment_term_partner_holiday/i18n/account_payment_term_partner_holiday.pot
odoo/addons/account_payment_term_partner_holiday/i18n/es.po
odoo/addons/account_payment_term_partner_holiday/models/__init__.py
odoo/addons/account_payment_term_partner_holiday/models/account_move.py
odoo/addons/account_payment_term_partner_holiday/models/account_payment_term.py
odoo/addons/account_payment_term_partner_holiday/models/res_partner.py
odoo/addons/account_payment_term_partner_holiday/readme/CONTRIBUTORS.rst
odoo/addons/account_payment_term_partner_holiday/readme/DESCRIPTION.rst
odoo/addons/account_payment_term_partner_holiday/readme/ROADMAP.rst
odoo/addons/account_payment_term_partner_holiday/readme/USAGE.rst
odoo/addons/account_payment_term_partner_holiday/security/ir.model.access.csv
odoo/addons/account_payment_term_partner_holiday/static/description/icon.png
odoo/addons/account_payment_term_partner_holiday/static/description/index.html
odoo/addons/account_payment_term_partner_holiday/tests/__init__.py
odoo/addons/account_payment_term_partner_holiday/tests/test_partner_holiday.py
odoo/addons/account_payment_term_partner_holiday/views/res_partner_view.xml
odoo14_addon_account_payment_term_partner_holiday-14.0.1.0.1.dev3.dist-info/METADATA
odoo14_addon_account_payment_term_partner_holiday-14.0.1.0.1.dev3.dist-info/WHEEL
odoo14_addon_account_payment_term_partner_holiday-14.0.1.0.1.dev3.dist-info/top_level.txt
odoo14_addon_account_payment_term_partner_holiday-14.0.1.0.1.dev3.dist-info/RECORD
